pyfidelimax
