Metadata-Version: 2.1
Name: pyfidelimax
Version: 1.0.3
Summary: fidelimax.com.br integration
Home-page: https://gitlab.com/yk2kus/pyfidelimax
Author: Yogesh Kushwaha
Author-email: info@tkopen.com
License: MIT
Platform: UNKNOWN
